homework2/2/modules.v
`define WORD_SIZE 32

//  Register File
module regfile(
        addr1, addr2, addr3, data1, data2, data3, clk, wr, rst
    );
    
    // Declare Input Variables
    input clk, wr, rst;
    input [4:0] addr1, addr2, addr3;
    input [`WORD_SIZE-1:0] data3;
    
    // Declare Output Variables
    output [`WORD_SIZE-1:0] data1, data2;
    
    // Reigsters
    reg [`WORD_SIZE-1:0] register[31:0];
    integer i;
    initial begin
        for (i = 0; i < 32; i = i + 1) begin
            register[i] = 32'h00000004;
        end
    end
    
    assign data1 = register[addr1];
    assign data2 = register[addr2];
   
    always @(posedge clk) begin
        if(rst) begin
            register[0] <= 0;
            register[1] <= 0;
            register[2] <= 0;
            register[3] <= 0;
        end
        if(wr) begin
            register[addr3] <= data3;
        end
    end
endmodule


module ALU (
    input  [31:0] A,
    input  [31:0] B,
    input  [2:0] ALUControl, // 000: ADD, 001: SUB, 010: AND, 011: OR, 101: SLT
    output reg [31:0] Result,
    output Zero
);

    always @(*) begin
        case (ALUControl)
            3'b000: Result = A + B;                      // ADD
            3'b001: Result = A - B;                      // SUB
            3'b010: Result = A & B;                      // AND
            3'b011: Result = A | B;                      // OR
            3'b101: Result = (A < B) ? 32'b1 : 32'b0;    // SLT (signed)
            3'b110: Result = A << B;
            default: Result = 32'b0;
        endcase
    end

    assign Zero = (Result == 32'b0);

endmodule


module data_memory (
    input              clk,
    input              rst,
    input              memWrite,               // 1: yaz
    input      [31:0]  addr,                   // adres (byte adresi)
    input      [31:0]  writeData,              // yazılacak veri (sw)
    output     [31:0]  readData                // okunan veri (lw)
);

    // 1024 kelimelik bellek (4KB)
    reg [31:0] memory [0:1023];
    reg [31:0] read_data_reg;
    assign readData = read_data_reg;

    integer i;
    // Belleği başlatma
    initial begin
        for (i = 0; i < 1024; i = i + 1) begin
            memory[i] = i; // isteğe bağlı başlangıç
        end
    end

    // Okuma (kombinasyonel)
    always @(*) begin
        read_data_reg = memory[addr[11:2]];
    end

    // Yazma (senkron)
    always @(posedge clk) begin
        if (rst) begin
            for (i = 0; i < 1024; i = i + 1) begin
                memory[i] <= 32'b0;
            end
        end
        else if (memWrite) begin
            memory[addr[11:2]] <= writeData;
        end
    end

endmodule




module mux1 (
    input  [`WORD_SIZE-1:0] in0,   // 0 seçilince gelen
    input  [`WORD_SIZE-1:0] in1,   // 1 seçilince gelen
    input                   ALUSrc,   // seçim sinyali (0 veya 1)
    output [`WORD_SIZE-1:0] SrcB    // seçilen çıkış
);

    assign SrcB = (ALUSrc == 1'b0) ? in0 : in1;

endmodule

module mux3 (
    input  [31:0] ALUResult,       // ALU'nun çıktısı
    input  [31:0] MemoryReadData,  // Bellekten okunan veri
    input  [31:0] PCPlus4,         // PC + 4
    input  [1:0]  ResultSrc,       // Seçim için kontrol sinyali
    output reg [31:0] wd3          // Seçilen veri, register'a yazılacak
);

    always @(*) begin
        case (ResultSrc)
            2'b00: wd3 = ALUResult;        // ALU sonucu
            2'b01: wd3 = MemoryReadData;   // Bellekten okunan veri
            2'b10: wd3 = PCPlus4;          // PC + 4 (jal)
            default: wd3 = 32'b0;          // Geçersiz durumda 0
        endcase
    end

endmodule


module extender(
    input [1:0] immSrc,           // immSrc: 2-bitlik seçim sinyali
    input [31:0] instr,           // instr: 32-bitlik talimat
    output reg [31:0] immExit     // immExit: 32-bitlik genişletilmiş sabit
);

    always @(*) begin
        case (immSrc)
            2'b00: immExit = { {20{instr[31]}}, instr[31:20] };                                   // I-type
            2'b01: immExit = { {20{instr[31]}}, instr[31:25], instr[11:7] };                      // S-type
            2'b10: immExit = { {19{instr[31]}}, instr[31], instr[7], instr[30:25], instr[11:8], 1'b0 }; // B-type
            2'b11: immExit = { {11{instr[31]}}, instr[31], instr[19:12], instr[20], instr[30:21], 1'b0 }; // J-type
            default: immExit = 32'b0; // Default: 0
        endcase
    end

endmodule



module pc_system (
    input clk,                             // Saat sinyali
    input rst,                             // Reset sinyali
    input pc_src,                          // PC seçim sinyali (0: PC+4, 1: branch_addr)
    input [31:0] immExit,              // Branch adresi
    output reg [31:0] pc_out               // Program counter çıktısı
);

    reg [31:0] pc_in;                     // Program counter girişi

    // PC + 4 hesapla
    wire [31:0] pc_plus4, branch_addr;
    assign pc_plus4 = pc_out + 4;
    assign branch_addr = pc_out + immExit;

    // MUX: next PC seçimi
    always @(*) begin
        if (pc_src == 1'b0)
            pc_in = pc_plus4;            // PC + 4 seç
        else
            pc_in = branch_addr;         // Branch adresini seç
    end

    // PC register'ını her pozitif kenarda güncelle
    always @(posedge clk or posedge rst) begin
        if (rst)
            pc_out <= 32'b0;             // Reset durumunda PC'yi sıfırla
        else
            pc_out <= pc_in;             // pc_in'i PC'ye aktar
    end

endmodule


module instruction_memory (
    input [31:0] address,   // Program Counter'dan gelen adres
    output reg [31:0] data_out // Bellekten okunan komut
);

    // Bellek boyutu, 256 adet 32-bit komut olsun
    reg [31:0] memory [0:255];

    // Belleği başlatmak için bir blok
    initial begin
        // Bellek adresine bazı komutlar yükleyelim

        memory[0] = 32'b00000000000000001001000100110011;
    end

    // Adrese göre komut okuma işlemi
    always @(*) begin
        // Bellekten veriyi okuma
        data_out = memory[address >> 2]; // Adresin 2'ye bölünüp index olarak kullanılmasını sağla (32-bitlik adres için)
    end
endmodule

homework2/2/controlUnit.v
module controlUnit(
    input [6:0] op,
    input [2:0] funct3,
    input funct7_5,
    input zero,
    output reg PCSrc,
    output reg [1:0] ResultSrc,
    output reg MemWrite,
    output reg ALUSrc,
    output reg [1:0] ImmSrc,
    output reg RegWrite,
    output reg [1:0] ALUOp,
    output reg [2:0] ALUControl
);

    reg Branch;
    reg Jump;

    always @(*) begin
        case(op)
            7'b0000011: begin // lw
                RegWrite = 1;
                ImmSrc = 2'b00;
                ALUSrc = 1;
                MemWrite = 0;
                ResultSrc = 2'b01;
                Branch = 0;
                ALUOp = 2'b00;
                Jump = 0;
            end

            7'b0100011: begin // sw
                RegWrite = 0;
                ImmSrc = 2'b01;
                ALUSrc = 1;
                MemWrite = 1;
                ResultSrc = 2'b00; // farketmez
                Branch = 0;
                ALUOp = 2'b00;
                Jump = 0;
            end

            7'b0110011: begin // R-Type
                RegWrite = 1;
                ImmSrc = 2'b00; // farketmez
                ALUSrc = 0;
                MemWrite = 0;
                ResultSrc = 2'b00;
                Branch = 0;
                ALUOp = 2'b10;
                Jump = 0;
            end

            7'b1100011: begin // beq
                RegWrite = 0;
                ImmSrc = 2'b10;
                ALUSrc = 0;
                MemWrite = 0;
                ResultSrc = 2'b01; // farketmez
                Branch = 1;
                ALUOp = 2'b01;
                Jump = 0;
            end

            7'b0010011: begin // I-Type ALU
                RegWrite = 1;
                ImmSrc = 2'b00;
                ALUSrc = 1; // farketmez
                MemWrite = 0;
                ResultSrc = 2'b00;
                Branch = 0;
                ALUOp = 2'b10;
                Jump = 0;
            end

            7'b1101111: begin // jal
                RegWrite = 1;
                ImmSrc = 2'b11;
                ALUSrc = 1; // farketmez
                MemWrite = 0;
                ResultSrc = 2'b10;
                Branch = 0;
                ALUOp = 2'b00; // farketmez
                Jump = 1;
            end

            default: begin
                RegWrite = 0;
                ImmSrc = 2'b00;
                ALUSrc = 0;
                MemWrite = 0;
                ResultSrc = 2'b00;
                Branch = 0;
                ALUOp = 2'b00;
                Jump = 0;
                PCSrc = 0;
            end        
        endcase
        PCSrc = (zero & Branch) | Jump;
    end

    always @(*) begin
        case (ALUOp)
            2'b00: ALUControl = 3'b000; // lw/sw → add
            2'b01: ALUControl = 3'b001; // beq → sub
            2'b10: begin
                case (funct3)
                    3'b000: begin
                        case ({op[5], funct7_5})
                            2'b00: ALUControl = 3'b000; // add
                            2'b01: ALUControl = 3'b000; // add
                            2'b10: ALUControl = 3'b000; // add
                            2'b11: ALUControl = 3'b001; // sub
                            default: ALUControl = 3'b000;
                        endcase
                    end
                    3'b010: ALUControl = 3'b101; // slt
                    3'b110: ALUControl = 3'b011; // or
                    3'b111: ALUControl = 3'b010; // and
                    3'b001: ALUControl = 3'b110; // sll
                    default: ALUControl = 3'b000;
                endcase
            end
            default: ALUControl = 3'b000;
        endcase
    end

endmodule

homework2/2/datapath.v
module processor (
    input clk,
    input rst
);
    // Internal Signals
    wire [31:0] pc_out, pc_in, instr;
    wire [31:0] read_data1, read_data2, alu_result, alu_b, mem_read_data , write_data;
    wire [1:0] result_src, imm_src, alu_op;
    wire reg_write, alu_src, mem_write, branch, pc_src, jump;
    wire [2:0] alu_control;
    wire [31:0] imm_out;
    wire zero;

    // Program Counter
    pc_system pc_unit (clk, rst, pc_src, imm_out, pc_out);

    // Instruction Memory (ICache)
    instruction_memory instr_mem (pc_out, instr);

    // Control Unit
    controlUnit ctrl_unit (instr[6:0], instr[14:12], instr[30], zero, pc_src, result_src, mem_write, alu_src, imm_src, reg_write, alu_op, alu_control);

    // Register File
    regfile rf (instr[19:15], instr[24:20], instr[11:7],read_data1, read_data2 , write_data, clk, reg_write, rst);

    // ALU
    ALU alu (read_data1, alu_b, alu_control, alu_result, zero);

    // MUX for ALUSrc
    mux1 alu_mux (read_data2, imm_out, alu_src, alu_b);

    // MUX for ResultSrca
    mux3 result_mux (alu_result, mem_read_data, (pc_out + 4), result_src, write_data);

    // Data Memory
    data_memory data_mem (clk, rst, mem_write, alu_result, read_data2, mem_read_data);

    // ImmExtender
    extender imm_ext (imm_src, instr, imm_out);

endmodule

homework2/3/datapath_tb.v
`timescale 1ns/1ps

module processor_tb;

    // Inputs
    reg clk;
    reg rst;

    // Instantiate the processor
    processor uut (
        .clk(clk),
        .rst(rst)
    );

    // Clock generation: 10ns period
    always #20 clk = ~clk;

    initial begin
        // Initialize Inputs
        clk = 0;
        rst = 1;

        // Apply reset
        #20;
        rst = 0;

        // Run simulation for a while
        #500;

        // Finish simulation
        $finish;
    end

    // Optional: waveform dump (for GTKWave)
    initial begin
        $dumpfile("processor_tb.vcd");
        $dumpvars(0, processor_tb);
    end

endmodule

homework2/2/processor_tb.vcd
$date
	Sun May 04 20:48:29 2025
$end
$version
	Icarus Verilog
$end
$timescale
	1ps
$end
$scope module processor_tb $end
$var reg 1 ! clk $end
$var reg 1 " rst $end
$scope module uut $end
$var wire 1 ! clk $end
$var wire 1 " rst $end
$var wire 1 # zero $end
$var wire 32 $ write_data [31:0] $end
$var wire 2 % result_src [1:0] $end
$var wire 1 & reg_write $end
$var wire 32 ' read_data2 [31:0] $end
$var wire 32 ( read_data1 [31:0] $end
$var wire 1 ) pc_src $end
$var wire 32 * pc_out [31:0] $end
$var wire 1 + mem_write $end
$var wire 32 , mem_read_data [31:0] $end
$var wire 32 - instr [31:0] $end
$var wire 2 . imm_src [1:0] $end
$var wire 32 / imm_out [31:0] $end
$var wire 1 0 alu_src $end
$var wire 32 1 alu_result [31:0] $end
$var wire 2 2 alu_op [1:0] $end
$var wire 3 3 alu_control [2:0] $end
$var wire 32 4 alu_b [31:0] $end
$scope module alu $end
$var wire 1 # Zero $end
$var wire 32 5 B [31:0] $end
$var wire 3 6 ALUControl [2:0] $end
$var wire 32 7 A [31:0] $end
$var reg 32 8 Result [31:0] $end
$upscope $end
$scope module alu_mux $end
$var wire 32 9 in1 [31:0] $end
$var wire 32 : in0 [31:0] $end
$var wire 32 ; SrcB [31:0] $end
$var wire 1 0 ALUSrc $end
$upscope $end
$scope module ctrl_unit $end
$var wire 3 < funct3 [2:0] $end
$var wire 1 = funct7_5 $end
$var wire 7 > op [6:0] $end
$var wire 1 # zero $end
$var reg 3 ? ALUControl [2:0] $end
$var reg 2 @ ALUOp [1:0] $end
$var reg 1 0 ALUSrc $end
$var reg 1 A Branch $end
$var reg 2 B ImmSrc [1:0] $end
$var reg 1 C Jump $end
$var reg 1 + MemWrite $end
$var reg 1 ) PCSrc $end
$var reg 1 & RegWrite $end
$var reg 2 D ResultSrc [1:0] $end
$upscope $end
$scope module data_mem $end
$var wire 32 E addr [31:0] $end
$var wire 1 ! clk $end
$var wire 1 + memWrite $end
$var wire 32 F readData [31:0] $end
$var wire 1 " rst $end
$var wire 32 G writeData [31:0] $end
$var reg 32 H read_data_reg [31:0] $end
$var integer 32 I i [31:0] $end
$upscope $end
$scope module imm_ext $end
$var wire 2 J immSrc [1:0] $end
$var wire 32 K instr [31:0] $end
$var reg 32 L immExit [31:0] $end
$upscope $end
$scope module instr_mem $end
$var wire 32 M address [31:0] $end
$var reg 32 N data_out [31:0] $end
$upscope $end
$scope module pc_unit $end
$var wire 1 ! clk $end
$var wire 32 O immExit [31:0] $end
$var wire 1 ) pc_src $end
$var wire 1 " rst $end
$var wire 32 P pc_plus4 [31:0] $end
$var wire 32 Q branch_addr [31:0] $end
$var reg 32 R pc_in [31:0] $end
$var reg 32 S pc_out [31:0] $end
$upscope $end
$scope module result_mux $end
$var wire 32 T ALUResult [31:0] $end
$var wire 32 U MemoryReadData [31:0] $end
$var wire 32 V PCPlus4 [31:0] $end
$var wire 2 W ResultSrc [1:0] $end
$var reg 32 X wd3 [31:0] $end
$upscope $end
$scope module rf $end
$var wire 5 Y addr1 [4:0] $end
$var wire 5 Z addr2 [4:0] $end
$var wire 5 [ addr3 [4:0] $end
$var wire 1 ! clk $end
$var wire 32 \ data1 [31:0] $end
$var wire 32 ] data2 [31:0] $end
$var wire 32 ^ data3 [31:0] $end
$var wire 1 " rst $end
$var wire 1 & wr $end
$var integer 32 _ i [31:0] $end
$upscope $end
$upscope $end
$upscope $end
$enddefinitions $end
$comment Show the parameter values. $end
$dumpall
$end
#0
$dumpvars
b100000 _
b1000000 ^
b100 ]
b100 \
b10 [
b0 Z
b1 Y
b1000000 X
b0 W
b100 V
b10000 U
b1000000 T
b0 S
b100 R
b0 Q
b100 P
b0 O
b1001000100110011 N
b0 M
b0 L
b1001000100110011 K
b0 J
b10000000000 I
b10000 H
b100 G
b10000 F
b1000000 E
b0 D
0C
b0 B
0A
b10 @
b110 ?
b110011 >
0=
b1 <
b100 ;
b100 :
b0 9
b1000000 8
b100 7
b110 6
b100 5
b100 4
b110 3
b10 2
b1000000 1
00
b0 /
b0 .
b1001000100110011 -
b10000 ,
0+
b0 *
0)
b100 (
b100 '
1&
b0 %
b1000000 $
0#
1"
0!
$end
#20000
bx ,
bx F
bx U
bx H
bx $
bx X
bx ^
bx 4
bx 5
bx ;
x#
bx 1
bx 8
bx E
bx T
b0 3
b0 6
b0 ?
b0 2
b0 @
0&
bx [
bx '
bx :
bx G
bx ]
bx Z
bx (
bx 7
bx \
bx Y
x=
bx <
bx >
bx /
bx 9
bx L
bx O
b1000 R
bx -
bx K
bx N
b1000 P
bx Q
b1000 V
b100 *
b100 M
b100 S
0"
1!
#40000
0!
#60000
b1100 R
b1100 P
b1100 V
b1000 *
b1000 M
b1000 S
1!
#80000
0!
#100000
b10000 R
b10000 P
b10000 V
b1100 *
b1100 M
b1100 S
1!
#120000
0!
#140000
b10100 R
b10100 P
b10100 V
b10000 *
b10000 M
b10000 S
1!
#160000
0!
#180000
b11000 R
b11000 P
b11000 V
b10100 *
b10100 M
b10100 S
1!
#200000
0!
#220000
b11100 R
b11100 P
b11100 V
b11000 *
b11000 M
b11000 S
1!
#240000
0!
#260000
b100000 R
b100000 P
b100000 V
b11100 *
b11100 M
b11100 S
1!
#280000
0!
#300000
b100100 R
b100100 P
b100100 V
b100000 *
b100000 M
b100000 S
1!
#320000
0!
#340000
b101000 R
b101000 P
b101000 V
b100100 *
b100100 M
b100100 S
1!
#360000
0!
#380000
b101100 R
b101100 P
b101100 V
b101000 *
b101000 M
b101000 S
1!
#400000
0!
#420000
b110000 R
b110000 P
b110000 V
b101100 *
b101100 M
b101100 S
1!
#440000
0!
#460000
b110100 R
b110100 P
b110100 V
b110000 *
b110000 M
b110000 S
1!
#480000
0!
#500000
b111000 R
b111000 P
b111000 V
b110100 *
b110100 M
b110100 S
1!
